autoarchive/__init__.py
autoarchive/admin.py
autoarchive/apps.py
autoarchive/models.py
autoarchive/tasks.py
django_autoarchive-0.0.3.dist-info/LICENSE
django_autoarchive-0.0.3.dist-info/METADATA
django_autoarchive-0.0.3.dist-info/WHEEL
django_autoarchive-0.0.3.dist-info/top_level.txt
django_autoarchive-0.0.3.dist-info/RECORD
